safespace/__init__.py
safespace/excs.py
safespace/middleware.py
safespace/py.typed
safespace/settings.py
safespace/templates/safespace/problem.html
django_safespace-0.6.0.dist-info/LICENSE
django_safespace-0.6.0.dist-info/METADATA
django_safespace-0.6.0.dist-info/WHEEL
django_safespace-0.6.0.dist-info/top_level.txt
django_safespace-0.6.0.dist-info/RECORD
