Metadata-Version: 2.1
Name: django-safespace
Version: 0.6.0
Summary: Exception catching and handling middleware for Django
Home-page: https://github.com/valohai/django-safespace
Author: Valohai
Maintainer: Aarni Koskela
Maintainer-email: akx@iki.fi
License: MIT
Platform: UNKNOWN
License-File: LICENSE
Requires-Dist: Django
Provides-Extra: dev
Requires-Dist: flake8 ; extra == 'dev'
Requires-Dist: isort (>=5.10) ; extra == 'dev'
Requires-Dist: pydocstyle ; extra == 'dev'
Requires-Dist: pytest-cov ; extra == 'dev'
Requires-Dist: pytest-django (>=3.0.0) ; extra == 'dev'
